physical_basis/__init__.py
physical_basis/eigenvalues.npy
physical_basis/eigenvectors.npy
physical_basis/physical_basis.py
physical_basis/torch/__init__.py
physical_basis/torch/physical_basis.py
physical_basis-1.0.0.dist-info/METADATA
physical_basis-1.0.0.dist-info/WHEEL
physical_basis-1.0.0.dist-info/top_level.txt
physical_basis-1.0.0.dist-info/RECORD
